LIFR/.DS_Store
LIFR/LIFR.py
LIFR/__init__.py
lifr-0.0.10.dist-info/METADATA
lifr-0.0.10.dist-info/WHEEL
lifr-0.0.10.dist-info/licenses/LICENSE
lifr-0.0.10.dist-info/RECORD
