Metadata-Version: 2.1
Name: LIFR
Version: 0.0.10
Summary: this package allows the user to connect with the LIFR model
Project-URL: Homepage, https://github.com/pypa/sampleproject
Project-URL: Bug Tracker, https://github.com/pypa/sampleproject/issues
Author-email: Raphael Scott <raphael.scott06@gmail.com>
License-File: LICENSE
Classifier: License :: OSI Approved :: MIT License
Classifier: Operating System :: OS Independent
Classifier: Programming Language :: Python :: 3
Requires-Python: >=3.1
